safecheck/__init__.py
safecheck/_overload.py
safecheck/_typecheck.py
safecheck/py.typed
safecheck-0.5.0.dist-info/METADATA
safecheck-0.5.0.dist-info/WHEEL
safecheck-0.5.0.dist-info/RECORD
