Metadata-Version: 2.3
Name: safecheck
Version: 0.5.0
Summary: Utilities for typechecking, shapechecking and dispatch.
License: MIT
Author: David Muhr
Author-email: muhrdavid+github@gmail.com
Requires-Python: >=3.10,<3.14
Classifier: Development Status :: 3 - Alpha
Classifier: Intended Audience :: Developers
Classifier: Intended Audience :: Education
Classifier: Intended Audience :: Science/Research
Classifier: License :: OSI Approved :: MIT License
Classifier: Operating System :: MacOS
Classifier: Operating System :: Microsoft :: Windows
Classifier: Operating System :: POSIX
Classifier: Operating System :: Unix
Classifier: Programming Language :: Python :: 3
Classifier: Programming Language :: Python :: 3.10
Classifier: Programming Language :: Python :: 3.11
Classifier: Programming Language :: Python :: 3.12
Classifier: Programming Language :: Python :: 3.13
Classifier: Programming Language :: Python :: 3 :: Only
Classifier: Topic :: Scientific/Engineering
Classifier: Topic :: Software Development :: Libraries
Classifier: Topic :: Utilities
Classifier: Typing :: Typed
Requires-Dist: beartype (>0.15,<0.21)
Requires-Dist: jaxtyping (>=0.2,<0.3)
Requires-Dist: typing-extensions (>=4.0,<5.0)
Project-URL: Homepage, https://github.com/davnn/safecheck
Project-URL: Repository, https://github.com/davnn/safecheck
